circuit.v
module circuit(
    input  wire       clk,        // 25MHz Ethernet TX Clock from PHY
    input  wire       rst,        // System Reset
    input  wire       send_btn,   // Button to trigger transmission
    output reg  [3:0] eth_txd,    // MII Data Nibbles
    output reg        eth_tx_en   // TX Enable (High while sending)
);

    // State Machine
    localparam IDLE     = 0,
               PREAMBLE = 1,
               SFD      = 2,
               PAYLOAD  = 3;

    reg [1:0] state = IDLE;
    reg [3:0] count = 0;
    reg [7:0] byte_count = 0;

    always @(posedge clk) begin
        if (rst) begin
            state <= IDLE;
            eth_tx_en <= 0;
        end else begin
            case (state)
                IDLE: begin
                    eth_tx_en <= 0;
                    if (send_btn) state <= PREAMBLE;
                end

                PREAMBLE: begin
                    eth_tx_en <= 1;
                    eth_txd <= 4'h5; // MII sends nibbles, 0x55 is 8'h5 then 8'h5
                    if (count == 13) begin // 7 bytes = 14 nibbles
                        state <= SFD;
                        count <= 0;
                    end else count <= count + 1;
                end

                SFD: begin
                    // SFD is 0xD5 (nibbles 5 then D)
                    if (count == 0) begin
                        eth_txd <= 4'h5;
                        count <= 1;
                    end else begin
                        eth_txd <= 4'hD;
                        state <= PAYLOAD;
                        count <= 0;
                    end
                end

                PAYLOAD: begin
                    eth_txd <= 4'hA; // Dummy Data
                    if (byte_count == 63) begin // Minimum 64 bytes
                        state <= IDLE;
                        byte_count <= 0;
                    end else byte_count <= byte_count + 1;
                end
            endcase
        end
    end
endmodule

waveform.vcd
$version Generated by VerilatedVcd $end
$timescale 1ps $end
 $scope module TOP $end
  $var wire 1 & clk $end
  $var wire 1 ' rst $end
  $var wire 1 ( send_btn $end
  $var wire 4 ) eth_txd [3:0] $end
  $var wire 1 * eth_tx_en $end
  $scope module circuit $end
   $var wire 1 & clk $end
   $var wire 1 ' rst $end
   $var wire 1 ( send_btn $end
   $var wire 4 ) eth_txd [3:0] $end
   $var wire 1 * eth_tx_en $end
   $var wire 32 + IDLE [31:0] $end
   $var wire 32 , PREAMBLE [31:0] $end
   $var wire 32 - SFD [31:0] $end
   $var wire 32 . PAYLOAD [31:0] $end
   $var wire 2 # state [1:0] $end
   $var wire 4 $ count [3:0] $end
   $var wire 8 % byte_count [7:0] $end
  $upscope $end
 $upscope $end
$enddefinitions $end


#0
b00 #
b0000 $
b00000000 %
1&
1'
0(
b0000 )
0*
b00000000000000000000000000000000 +
b00000000000000000000000000000001 ,
b00000000000000000000000000000010 -
b00000000000000000000000000000011 .
#5
0&
#10
1&
#15
0&
#20
1&
0'
#25
0&
#30
1&
#35
0&
#40
1&
#45
0&
#50
b01 #
1&
1(
#55
0&
#60
b0001 $
1&
b0101 )
1*
#65
0&
#70
b0010 $
1&
#75
0&
#80
b0011 $
1&
#85
0&
#90
b0100 $
1&
#95
0&
#100
b0101 $
1&
0(
#105
0&
#110
b0110 $
1&
#115
0&
#120
b0111 $
1&
#125
0&
#130
b1000 $
1&
#135
0&
#140
b1001 $
1&
#145
0&
#150
b1010 $
1&
#155
0&
#160
b1011 $
1&
#165
0&
#170
b1100 $
1&
#175
0&
#180
b1101 $
1&
#185
0&
#190
b10 #
b0000 $
1&
#195
0&
#200
b0001 $
1&
#205
0&
#210
b11 #
b0000 $
1&
b1101 )
#215
0&
#220
b00000001 %
1&
b1010 )
#225
0&
#230
b00000010 %
1&
#235
0&
#240
b00000011 %
1&
#245
0&
#250
b00000100 %
1&
#255
0&
#260
b00000101 %
1&
#265
0&
#270
b00000110 %
1&
#275
0&
#280
b00000111 %
1&
#285
0&
#290
b00001000 %
1&
#295
0&
#300
b00001001 %
1&
#305
0&
#310
b00001010 %
1&
#315
0&
#320
b00001011 %
1&
#325
0&
#330
b00001100 %
1&
#335
0&
#340
b00001101 %
1&
#345
0&
#350
b00001110 %
1&
#355
0&
#360
b00001111 %
1&
#365
0&
#370
b00010000 %
1&
#375
0&
#380
b00010001 %
1&
#385
0&
#390
b00010010 %
1&
#395
0&
#400
b00010011 %
1&
#405
0&
#410
b00010100 %
1&
#415
0&
#420
b00010101 %
1&
#425
0&
#430
b00010110 %
1&
#435
0&
#440
b00010111 %
1&
#445
0&
#450
b00011000 %
1&
#455
0&
#460
b00011001 %
1&
#465
0&
#470
b00011010 %
1&
#475
0&
#480
b00011011 %
1&
#485
0&
#490
b00011100 %
1&
#495
0&
#500
b00011101 %
1&
#505
0&
#510
b00011110 %
1&
#515
0&
#520
b00011111 %
1&
#525
0&
#530
b00100000 %
1&
#535
0&
#540
b00100001 %
1&
#545
0&
#550
b00100010 %
1&
#555
0&
#560
b00100011 %
1&
#565
0&
#570
b00100100 %
1&
#575
0&
#580
b00100101 %
1&
#585
0&
#590
b00100110 %
1&
#595
0&
#600
b00100111 %
1&
#605
0&
#610
b00101000 %
1&
#615
0&
#620
b00101001 %
1&
#625
0&
#630
b00101010 %
1&
#635
0&
#640
b00101011 %
1&
#645
0&
#650
b00101100 %
1&
#655
0&
#660
b00101101 %
1&
#665
0&
#670
b00101110 %
1&
#675
0&
#680
b00101111 %
1&
#685
0&
#690
b00110000 %
1&
#695
0&
#700
b00110001 %
1&
#705
0&
#710
b00110010 %
1&
#715
0&
#720
b00110011 %
1&
#725
0&
#730
b00110100 %
1&
#735
0&
#740
b00110101 %
1&
#745
0&
#750
b00110110 %
1&
#755
0&
#760
b00110111 %
1&
#765
0&
#770
b00111000 %
1&
#775
0&
#780
b00111001 %
1&
#785
0&
#790
b00111010 %
1&
#795
0&
#800
b00111011 %
1&
#805
0&
#810
b00111100 %
1&
#815
0&
#820
b00111101 %
1&
#825
0&
#830
b00111110 %
1&
#835
0&
#840
b00111111 %
1&
#845
0&
#850
b00 #
b00000000 %
1&
